makefast/__init__.py
makefast/cli.py
makefast/app/__init__.py
makefast/app/routes.py
makefast/app/dependencies/__init__.py
makefast/app/dependencies/response_handler.py
makefast/app/enums/__init__.py
makefast/app/migrations/__init__.py
makefast/app/models/__init__.py
makefast/app/routes/__init__.py
makefast/app/schemes/__init__.py
makefast/app/tests/__init__.py
makefast/app/tests/test_database/__init__.py
makefast/app/tests/test_database/mongodb_test.py
makefast/app/tests/test_database/mysql_test.py
makefast/base_model/__init__.py
makefast/base_model/mongodb.py
makefast/base_model/mysql.py
makefast/command/__init__.py
makefast/command/create_enum.py
makefast/command/create_migration.py
makefast/command/create_model.py
makefast/command/create_route.py
makefast/command/create_scheme.py
makefast/command/execute_migrations.py
makefast/command/project_init.py
makefast/database/__init__.py
makefast/database/mongodb.py
makefast/database/mysql.py
makefast/migration/__init__.py
makefast/migration/create.py
makefast/migration/mongodb.py
makefast/utils/__init__.py
makefast/utils/common.py
makefast-2.2.6.dist-info/LICENSE
makefast-2.2.6.dist-info/METADATA
makefast-2.2.6.dist-info/WHEEL
makefast-2.2.6.dist-info/entry_points.txt
makefast-2.2.6.dist-info/top_level.txt
makefast-2.2.6.dist-info/RECORD
