Metadata-Version: 2.1
Name: makefast
Version: 2.2.6
Summary: FastAPI CLI Library
License-File: LICENSE
Requires-Dist: typer~=0.12.5
Requires-Dist: setuptools~=73.0.1
Requires-Dist: click~=8.1.7
Requires-Dist: motor~=3.6.0
Requires-Dist: pytest~=8.3.3
Requires-Dist: pymongo~=4.9.2
Requires-Dist: pydantic~=2.8.2
Requires-Dist: python-dotenv~=1.0.1
Requires-Dist: mysql-connector-python~=9.0.0
Requires-Dist: starlette~=0.38.2
